pyspextool/__init__.py
pyspextool/config.py
pyspextool/pyspextoolerror.py
pyspextool/setup_utils.py
pyspextool/batch/__init__.py
pyspextool/batch/batch.py
pyspextool/batch/batch_cl.py
pyspextool/batch/log_template.txt
pyspextool/batch/observer_schedule.csv
pyspextool/batch/observer_schedule_compact.csv
pyspextool/batch/qa.css
pyspextool/batch/qa_singleplot_template.txt
pyspextool/batch/qa_source_template.txt
pyspextool/batch/qa_template.txt
pyspextool/combine/__init__.py
pyspextool/combine/combine.py
pyspextool/combine/combine_spectra.py
pyspextool/combine/config.py
pyspextool/combine/load_spectra.py
pyspextool/combine/qaplots.py
pyspextool/combine/scale_spectra.py
pyspextool/data/HI.dat
pyspextool/data/Vega50000_new.fits
pyspextool/data/atran100.fits
pyspextool/data/atran1000.fits
pyspextool/data/atran200.fits
pyspextool/data/atran2000.fits
pyspextool/data/atran300.fits
pyspextool/data/atran3000.fits
pyspextool/data/atran400.fits
pyspextool/data/atran4000.fits
pyspextool/data/atran500.fits
pyspextool/data/atran600.fits
pyspextool/data/atran700.fits
pyspextool/data/atran800.fits
pyspextool/data/atran900.fits
pyspextool/data/pyspextool_keywords.dat
pyspextool/data/sptype_effectivetemperature.dat
pyspextool/extract/__init__.py
pyspextool/extract/background_subtraction.py
pyspextool/extract/combine_images.py
pyspextool/extract/config.py
pyspextool/extract/define_aperture_parameters.py
pyspextool/extract/do_all_steps.py
pyspextool/extract/extract.py
pyspextool/extract/extract_apertures.py
pyspextool/extract/extraction.py
pyspextool/extract/flat.py
pyspextool/extract/identify_apertures.py
pyspextool/extract/images.py
pyspextool/extract/load_image.py
pyspextool/extract/make_flat.py
pyspextool/extract/make_profiles.py
pyspextool/extract/make_wavecal.py
pyspextool/extract/override_aperturesigns.py
pyspextool/extract/profiles.py
pyspextool/extract/select_orders.py
pyspextool/extract/trace.py
pyspextool/extract/trace_apertures.py
pyspextool/extract/wavecal.py
pyspextool-1.6b4.dist-info/licenses/LICENSE
pyspextool-1.6b4.dist-info/METADATA
pyspextool-1.6b4.dist-info/WHEEL
pyspextool-1.6b4.dist-info/top_level.txt
pyspextool-1.6b4.dist-info/RECORD
