Metadata-Version: 2.4
Name: pyspextool
Version: 1.6b4
Classifier: Programming Language :: Python :: 3
Requires-Python: >=3.10
License-File: LICENSE
Requires-Dist: astropy
Requires-Dist: scipy
Requires-Dist: matplotlib
Requires-Dist: numpy<2.0
Requires-Dist: pandas
Requires-Dist: importlib_resources; python_version < "3.11"
Requires-Dist: git-lfs
Requires-Dist: astroquery>0.4.8
Requires-Dist: specutils
Requires-Dist: dust_extinction
Requires-Dist: jinja2
Requires-Dist: pooch
Provides-Extra: test
Requires-Dist: pytest; extra == "test"
Requires-Dist: ruff; extra == "test"
Dynamic: license-file
